[
  {
    "id": "1",
    "name": "LED Blinking with 555 Timer",
    "shortDescription": "A classic beginner project to make an LED flash using a 555 timer IC.",
    "theory": "The 555 timer operates in astable mode, producing a square wave output that turns the LED on and off at a regular interval determined by the resistors and capacitor.",
    "components": [
      { "name": "555 Timer IC", "quantity": 1, "priceInINR": 15 },
      { "name": "LED (Red)", "quantity": 1, "priceInINR": 2 },
      { "name": "Resistor 1k Ohm", "quantity": 1, "priceInINR": 1 },
      { "name": "Resistor 10k Ohm", "quantity": 1, "priceInINR": 1 },
      { "name": "Capacitor 10uF", "quantity": 1, "priceInINR": 5 },
      { "name": "9V Battery", "quantity": 1, "priceInINR": 20 },
      { "name": "Breadboard", "quantity": 1, "priceInINR": 100 },
      { "name": "Jumper Wires", "quantity": 5, "priceInINR": 10 }
    ],
    "steps": [
      "Place the 555 timer on the breadboard.",
      "Connect pin 1 to Ground (GND).",
      "Connect pin 8 to VCC (9V).",
      "Connect pin 4 to VCC.",
      "Connect the 10uF capacitor between pin 2 and Ground.",
      "Connect pin 2 to pin 6.",
      "Connect the 10k resistor between pin 7 and VCC.",
      "Connect the 1k resistor between pin 7 and pin 6.",
      "Connect the LED anode to pin 3 and cathode to Ground via a resistor."
    ],
    "layout3d": {
      "components": [
        { "type": "ic", "position": [0, 0.2, 0], "color": "#333333", "size": [1, 0.2, 0.6], "label": "555" },
        { "type": "led", "position": [2, 0.2, 0], "color": "red", "size": [0.2, 0.4, 0.2], "label": "LED" },
        { "type": "resistor", "position": [1, 0.2, 1], "color": "#d2b48c", "size": [0.6, 0.1, 0.2], "label": "1k" },
        { "type": "battery", "position": [-3, 0.5, 0], "color": "black", "size": [1, 1, 0.5], "label": "9V" }
      ],
      "wires": [
        { "start": [-2.5, 0.5, 0], "end": [0, 0.2, -0.3], "color": "red" },
        { "start": [-2.5, 0.5, 0], "end": [0, 0.2, 0.3], "color": "black" },
        { "start": [0.5, 0.2, 0], "end": [2, 0.2, 0], "color": "yellow" }
      ]
    }
  },
  {
    "id": "2",
    "name": "5V Regulated Power Supply",
    "shortDescription": "Convert 9V or 12V DC to a stable 5V DC output using the 7805 regulator.",
    "theory": "The 7805 voltage regulator IC takes a higher input voltage and maintains a constant 5V output, which is essential for powering many digital circuits.",
    "components": [
      { "name": "7805 Voltage Regulator", "quantity": 1, "priceInINR": 10 },
      { "name": "Capacitor 100uF", "quantity": 1, "priceInINR": 5 },
      { "name": "Capacitor 10uF", "quantity": 1, "priceInINR": 3 },
      { "name": "9V Battery", "quantity": 1, "priceInINR": 20 },
      { "name": "Breadboard", "quantity": 1, "priceInINR": 100 }
    ],
    "steps": [
      "Place the 7805 regulator on the breadboard.",
      "Connect the Input pin (1) to the positive terminal of the battery.",
      "Connect the Ground pin (2) to the negative terminal.",
      "Connect the 100uF capacitor between Input and Ground.",
      "Connect the 10uF capacitor between Output (3) and Ground.",
      "Measure the voltage across Output and Ground to verify 5V."
    ],
    "layout3d": {
      "components": [
        { "type": "ic", "position": [0, 0.5, 0], "color": "black", "size": [0.5, 0.5, 0.2], "label": "7805" },
        { "type": "capacitor", "position": [-1, 0.3, 0], "color": "blue", "size": [0.3, 0.6, 0.3], "label": "100uF" },
        { "type": "capacitor", "position": [1, 0.3, 0], "color": "blue", "size": [0.3, 0.4, 0.3], "label": "10uF" },
        { "type": "battery", "position": [-3, 0.5, 0], "color": "black", "size": [1, 1, 0.5], "label": "9V" }
      ],
      "wires": [
        { "start": [-2.5, 0.5, 0], "end": [-0.25, 0.5, 0], "color": "red" },
        { "start": [-2.5, 0.5, 0], "end": [0, 0.2, 0], "color": "black" }
      ]
    }
  },
  {
    "id": "3",
    "name": "LDR Automatic Street Light",
    "shortDescription": "Turns on an LED automatically when it gets dark using a Light Dependent Resistor.",
    "theory": "An LDR changes its resistance based on light intensity. When used in a voltage divider circuit with a transistor, it can switch a load (LED) on or off depending on ambient light.",
    "components": [
      { "name": "LDR (Light Dependent Resistor)", "quantity": 1, "priceInINR": 10 },
      { "name": "BC547 Transistor", "quantity": 1, "priceInINR": 5 },
      { "name": "Resistor 10k Ohm", "quantity": 1, "priceInINR": 1 },
      { "name": "Resistor 330 Ohm", "quantity": 1, "priceInINR": 1 },
      { "name": "LED (White)", "quantity": 1, "priceInINR": 3 },
      { "name": "9V Battery", "quantity": 1, "priceInINR": 20 }
    ],
    "steps": [
      "Place the BC547 transistor on the breadboard.",
      "Connect the emitter to Ground.",
      "Connect the LDR between the base and VCC.",
      "Connect the 10k resistor between the base and Ground.",
      "Connect the LED anode to VCC via the 330 ohm resistor.",
      "Connect the LED cathode to the collector of the transistor."
    ],
    "layout3d": {
      "components": [
        { "type": "transistor", "position": [0, 0.3, 0], "color": "black", "size": [0.3, 0.3, 0.2], "label": "BC547" },
        { "type": "ldr", "position": [-1, 0.1, 0], "color": "orange", "size": [0.4, 0.1, 0.4], "label": "LDR" },
        { "type": "led", "position": [1, 0.3, 0], "color": "white", "size": [0.2, 0.4, 0.2], "label": "LED" },
        { "type": "battery", "position": [-3, 0.5, 0], "color": "black", "size": [1, 1, 0.5], "label": "9V" }
      ],
      "wires": [
        { "start": [-3, 0.5, 0], "end": [-1, 0.1, 0], "color": "red" },
        { "start": [-1, 0.1, 0], "end": [0, 0.3, 0], "color": "green" }
      ]
    }
  }
]
